safesubs/__init__.py
safesubs/client.py
safesubs-0.2.4.dist-info/METADATA
safesubs-0.2.4.dist-info/WHEEL
safesubs-0.2.4.dist-info/top_level.txt
safesubs-0.2.4.dist-info/RECORD
