Metadata-Version: 2.4
Name: safesubs
Version: 0.2.4
Summary: Проверка обязательных подписок пользователей в Telegram ботах с локальным кэшем
Author-email: PGSAVE <i@sxve.it>
License: MIT
Project-URL: Homepage, https://github.com/PGSAVE/safesubs
Project-URL: Repository, https://github.com/PGSAVE/safesubs
Requires-Python: >=3.9
Requires-Dist: aiohttp<=3.11.18
